{
  "1": {
    "repoFullName": "Wilfred/difftastic",
    "totalPoints": 56309,
    "avatar": "https://avatars.githubusercontent.com/u/70800?v=4"
  },
  "2": {
    "repoFullName": "Lissy93/dashy",
    "totalPoints": 54000.5,
    "avatar": "https://avatars.githubusercontent.com/u/1862727?v=4"
  },
  "3": {
    "repoFullName": "Lissy93/personal-security-checklist",
    "totalPoints": 48385,
    "avatar": "https://avatars.githubusercontent.com/u/1862727?v=4"
  },
  "4": {
    "repoFullName": "TodePond/GulfOfMexico",
    "totalPoints": 30686,
    "avatar": "https://avatars.githubusercontent.com/u/15892272?v=4"
  },
  "5": {
    "repoFullName": "orf/gping",
    "totalPoints": 29452.5,
    "avatar": "https://avatars.githubusercontent.com/u/1027207?v=4"
  },
  "6": {
    "repoFullName": "darrenburns/posting",
    "totalPoints": 23626,
    "avatar": "https://avatars.githubusercontent.com/u/5740731?v=4"
  },
  "7": {
    "repoFullName": "steipete/Aspects",
    "totalPoints": 21548.5,
    "avatar": "https://avatars.githubusercontent.com/u/58493?v=4"
  },
  "8": {
    "repoFullName": "Lissy93/awesome-privacy",
    "totalPoints": 20194.5,
    "avatar": "https://avatars.githubusercontent.com/u/1862727?v=4"
  },
  "9": {
    "repoFullName": "mvdan/sh",
    "totalPoints": 19713.5,
    "avatar": "https://avatars.githubusercontent.com/u/3576549?v=4"
  },
  "10": {
    "repoFullName": "HariSekhon/DevOps-Bash-tools",
    "totalPoints": 17881,
    "avatar": "https://avatars.githubusercontent.com/u/2211051?v=4"
  }
}